stubalyzer/__init__.py
stubalyzer/__main__.py
stubalyzer/analyze.py
stubalyzer/analyze_test.py
stubalyzer/analyze_unit_test.py
stubalyzer/collect.py
stubalyzer/collect_test.py
stubalyzer/compare.py
stubalyzer/compare_test.py
stubalyzer/compare_typevars_test.py
stubalyzer/conftest.py
stubalyzer/lookup.py
stubalyzer/lookup_test.py
stubalyzer/py.typed
stubalyzer/types.py
stubalyzer/utils.py
stubalyzer/utils_unit_test.py
stubalyzer/stubs/expected_mismatches.json
stubalyzer/stubs/pytest.pyi
stubalyzer/stubs/schema.pyi
stubalyzer/stubs/_pytest/__init__.pyi
stubalyzer/stubs/_pytest/capture.pyi
stubalyzer/stubs/_pytest/fixtures.pyi
stubalyzer/stubs/_pytest/python_api.pyi
stubalyzer/stubs/_pytest/_code/__init__.pyi
stubalyzer/stubs/_pytest/_code/code.pyi
stubalyzer-0.5.1.dist-info/entry_points.txt
stubalyzer-0.5.1.dist-info/LICENSE
stubalyzer-0.5.1.dist-info/WHEEL
stubalyzer-0.5.1.dist-info/METADATA
stubalyzer-0.5.1.dist-info/RECORD
