Metadata-Version: 2.1
Name: stubalyzer
Version: 0.5.1
Summary: Analysis tool comparing hand written stubs to stubgen-generated ones, reporting inconsistencies
Keywords: mypy,analysis,stubgen,stubs
Author-email: Kialo GmbH <open-source@kialo.com>
Requires-Python: >=3.9
Classifier: Development Status :: 3 - Alpha
Classifier: Intended Audience :: Developers
Classifier: Topic :: Software Development :: Build Tools
Classifier: Typing :: Typed
Classifier: License :: OSI Approved :: MIT License
Classifier: Programming Language :: Python :: 3
Classifier: Programming Language :: Python :: 3.9
Requires-Dist: mypy==0.930
Requires-Dist: schema>=0.7.5
Requires-Dist: bump2version>=1.0.1 ; extra == "dev"
Requires-Dist: pre-commit>=2.20.0 ; extra == "dev"
Requires-Dist: black==22.6.0 ; extra == "dev"
Requires-Dist: flake8==4.0.1 ; extra == "dev"
Requires-Dist: flake8-rst-docstrings==0.2.7 ; extra == "dev"
Requires-Dist: isort==5.10.1 ; extra == "dev"
Requires-Dist: Sphinx>=2.2.0 ; extra == "doc"
Requires-Dist: Pygments ; extra == "doc"
Requires-Dist: sphinx-rtd-theme ; extra == "doc"
Requires-Dist: pytest>=6.2.5 ; extra == "test"
Requires-Dist: attrs==19.3.0 ; extra == "test"
Project-URL: Bug Reports, https://github.com/kialo/stubalyzer/issues
Project-URL: Home, https://github.com/kialo/stubalyzer
Provides-Extra: dev
Provides-Extra: doc
Provides-Extra: test
